dayu_timecode/__init__.py
dayu_timecode/base.py
dayu_timecode/config.py
dayu_timecode/data_structure.py
dayu_timecode/dispatch.py
dayu_timecode/error.py
dayu_timecode-0.2.dist-info/METADATA
dayu_timecode-0.2.dist-info/RECORD
dayu_timecode-0.2.dist-info/WHEEL
dayu_timecode-0.2.dist-info/top_level.txt
tests/__init__.py
tests/test_dayuTimeCode.py
tests/test_dayuTimeRange.py
