Metadata-Version: 2.1
Name: dayu-timecode
Version: 0.2
Summary: timecode lib for human. support SMPTE non-drop frame and drop frames and many other timecode formats.
Home-page: https://github.com/phenom-films/dayu_timecode
Author: Andy Guo
Author-email: technology@phenom-films.com
Maintainer: Andy Guo
Maintainer-email: andyguo@phenom-films.com
License: MIT
Platform: dayu_timecode
Classifier: Operating System :: OS Independent
Classifier: Programming Language :: Python
Classifier: Programming Language :: Python :: Implementation
Classifier: Programming Language :: Python :: 2
Classifier: Programming Language :: Python :: 2.7
